ipython_mcp/__init__.py
ipython_mcp/__main__.py
ipython_mcp/default_connection.json
ipython_mcp/server.py
ipython_mcp-0.1.0.dist-info/licenses/LICENSE
ipython_mcp-0.1.0.dist-info/METADATA
ipython_mcp-0.1.0.dist-info/WHEEL
ipython_mcp-0.1.0.dist-info/entry_points.txt
ipython_mcp-0.1.0.dist-info/top_level.txt
ipython_mcp-0.1.0.dist-info/RECORD
