Metadata-Version: 2.4
Name: ipython-mcp
Version: 0.1.0
Summary: MCP Server for IPython kernel integration
Author-email: Gabi Teodoru <gabiteodoru@gmail.com>
License: MIT
Project-URL: Homepage, https://github.com/gabiteodoru/ipython-mcp
Project-URL: Bug Tracker, https://github.com/gabiteodoru/ipython-mcp/issues
Project-URL: Source Code, https://github.com/gabiteodoru/ipython-mcp
Requires-Python: >=3.8
License-File: LICENSE
Requires-Dist: mcp
Requires-Dist: pyzmq
Requires-Dist: ipython
Dynamic: license-file
